ethwallet/__init__.py
ethwallet-0.1.dist-info/METADATA
ethwallet-0.1.dist-info/WHEEL
ethwallet-0.1.dist-info/top_level.txt
ethwallet-0.1.dist-info/RECORD
