Metadata-Version: 2.1
Name: ethwallet
Version: 0.1
Summary: Prints USD value of tokens and total.
Home-page: UNKNOWN
Author: UNKNOWN
Author-email: UNKNOWN
License: MIT
Platform: UNKNOWN
